{
  "project_info": {
    "project_number": "206944051255",
    "firebase_url": "https://firechat-ce485.firebaseio.com",
    "project_id": "firechat-ce485",
    "storage_bucket": "firechat-ce485.appspot.com"
  },
  "client": [
    {
      "client_info": {
        "mobilesdk_app_id": "1:206944051255:android:bbcf32a0d6d435da",
        "android_client_info": {
          "package_name": "com.example.projekt.klientutveckling.firechat"
        }
      },
      "oauth_client": [
        {
          "client_id": "206944051255-tjq1853kku3luoaal0s6n2qqdbigt6id.apps.googleusercontent.com",
          "client_type": 1,
          "android_info": {
            "package_name": "com.example.projekt.klientutveckling.firechat",
            "certificate_hash": "f0b31aa59a8722cc77cf2c42da0e438f8ca86b90"
          }
        },
        {
          "client_id": "206944051255-nkne44oalsav8brbccaqcss4slo3s46h.apps.googleusercontent.com",
          "client_type": 1,
          "android_info": {
            "package_name": "com.example.projekt.klientutveckling.firechat",
            "certificate_hash": "d5767ac3cf6042a11032a6221e2231e021b7ed49"
          }
        },
        {
          "client_id": "206944051255-8rqqllodfr872ahl4ei53gd5as78nnts.apps.googleusercontent.com",
          "client_type": 1,
          "android_info": {
            "package_name": "com.example.projekt.klientutveckling.firechat",
            "certificate_hash": "79929da438ac2bc26630299670e1bef0e221e2a4"
          }
        },
        {
          "client_id": "206944051255-pd6cm4viq786u1k2p95q7t7bpahmqroo.apps.googleusercontent.com",
          "client_type": 1,
          "android_info": {
            "package_name": "com.example.projekt.klientutveckling.firechat",
            "certificate_hash": "369cf3a68453db258fb34a35663412f02eb1fe81"
          }
        },
        {
          "client_id": "206944051255-jf7qcdc8muoov97uqc9j137c4le9u1ou.apps.googleusercontent.com",
          "client_type": 1,
          "android_info": {
            "package_name": "com.example.projekt.klientutveckling.firechat",
            "certificate_hash": "37930a6f3521c351768dad005962fda15b132c04"
          }
        },
        {
          "client_id": "206944051255-m1f6s4va2dbmfjimubb0n64rklbk3as1.apps.googleusercontent.com",
          "client_type": 1,
          "android_info": {
            "package_name": "com.example.projekt.klientutveckling.firechat",
            "certificate_hash": "4aa16ea3363c9770e2f7e1265e74e2cbd86ce41b"
          }
        },
        {
          "client_id": "206944051255-6gceer9katpc1qlg9ajd2ftgid7foe3q.apps.googleusercontent.com",
          "client_type": 3
        }
      ],
      "api_key": [
        {
          "current_key": "AIzaSyC5P2op60oNYVlapjESJwQZaxtcoNCg2gU"
        }
      ],
      "services": {
        "analytics_service": {
          "status": 1
        },
        "appinvite_service": {
          "status": 2,
          "other_platform_oauth_client": [
            {
              "client_id": "206944051255-6gceer9katpc1qlg9ajd2ftgid7foe3q.apps.googleusercontent.com",
              "client_type": 3
            }
          ]
        },
        "ads_service": {
          "status": 2
        }
      }
    }
  ],
  "configuration_version": "1"
}